__init__.py
main.py
aStarEngine_package/algorithms/__init__.py
aStarEngine_package/algorithms/aStar_custom.py
aStarEngine_package/algorithms/aStar_multi.py
aStarEngine_package/utils/__init__.py
aStarEngine_package/utils/routing.py
aStarEngine_package-1.0.0.dist-info/LICENSE
aStarEngine_package-1.0.0.dist-info/METADATA
aStarEngine_package-1.0.0.dist-info/WHEEL
aStarEngine_package-1.0.0.dist-info/top_level.txt
aStarEngine_package-1.0.0.dist-info/RECORD
