Metadata-Version: 2.1
Name: aStarEngine_package
Version: 1.0.0
Summary: A package to find the shortest path in a map with up to 5 intermediate stops, using A*
Author-email: Sathyanarayanan RS <sathya05@vt.edu>
Project-URL: Homepage, https://github.com/Sathyanarayanan-ops/map_engine
Project-URL: Issues, https://github.com/Sathyanarayanan-ops/map_engine/issues
Classifier: Programming Language :: Python :: 3
Classifier: License :: OSI Approved :: MIT License
Classifier: Operating System :: OS Independent
Classifier: Intended Audience :: Developers
Classifier: Topic :: Software Development :: Libraries
Requires-Python: >=3.8
License-File: LICENSE
